{
  "indexes": [
    {
      "collectionGroup": "tasks",
      "queryScope": "COLLECTION",
      "fields": [
        {
          "fieldPath": "status",
          "order": "ASCENDING"
        },
        {
          "fieldPath": "subject",
          "order": "ASCENDING"
        },
        {
          "fieldPath": "createdAt",
          "order": "DESCENDING"
        }
      ]
    },
    {
      "collectionGroup": "tasks",
      "queryScope": "COLLECTION",
      "fields": [
        {
          "fieldPath": "status",
          "order": "ASCENDING"
        },
        {
          "fieldPath": "reservedUntil",
          "order": "ASCENDING"
        }
      ]
    },
    {
      "collectionGroup": "invites",
      "queryScope": "COLLECTION",
      "fields": [
        {
          "fieldPath": "taskId",
          "order": "ASCENDING"
        },
        {
          "fieldPath": "expertId",
          "order": "ASCENDING"
        }
      ]
    },
    {
      "collectionGroup": "users",
      "queryScope": "COLLECTION",
      "fields": [
        {
          "fieldPath": "subjects",
          "arrayConfig": "CONTAINS"
        },
        {
          "fieldPath": "ratingAvg",
          "order": "ASCENDING"
        },
        {
          "fieldPath": "ratingCount",
          "order": "ASCENDING"
        }
      ]
    },
    {
      "collectionGroup": "tasks",
      "queryScope": "COLLECTION",
      "fields": [
        {
          "fieldPath": "matching.nextWaveAt",
          "order": "ASCENDING"
        },
        {
          "fieldPath": "status",
          "order": "ASCENDING"
        }
      ]
    },
    {
      "collectionGroup": "tasks",
      "queryScope": "COLLECTION",
      "fields": [
        {
          "fieldPath": "reservedBy",
          "order": "ASCENDING"
        },
        {
          "fieldPath": "status",
          "order": "ASCENDING"
        },
        {
          "fieldPath": "reservedUntil",
          "order": "ASCENDING"
        }
      ]
    }
  ],
  "fieldOverrides": []
}
